pycollisiondb/__init__.py
pycollisiondb/pycoll_ds.py
pycollisiondb/pycollisiondb.py
pycollisiondb-0.1.6.dist-info/LICENSE
pycollisiondb-0.1.6.dist-info/METADATA
pycollisiondb-0.1.6.dist-info/WHEEL
pycollisiondb-0.1.6.dist-info/top_level.txt
pycollisiondb-0.1.6.dist-info/RECORD
