Metadata-Version: 2.2
Name: pycollisiondb
Version: 0.1.6
Summary: A package for interacting with CollisionDB
Home-page: https://github.com/xnx/pycollisiondb
Author: Christian Hill
Author-email: ch.hill@iaea.org
Project-URL: Bug Reports, https://github.com/xnx/pycollisiondb/issues
Keywords: chemistry,formula,species,state,reaction
Classifier: Development Status :: 4 - Beta
Classifier: Intended Audience :: Science/Research
Classifier: Topic :: Scientific/Engineering :: Chemistry
Classifier: Topic :: Scientific/Engineering :: Physics
Classifier: License :: OSI Approved :: Apache Software License
Classifier: Programming Language :: Python :: 3
Classifier: Programming Language :: Python :: 3.8
Classifier: Programming Language :: Python :: 3.9
Classifier: Programming Language :: Python :: 3.10
Classifier: Programming Language :: Python :: 3.11
Classifier: Programming Language :: Python :: 3.12
Classifier: Programming Language :: Python :: 3.13
Classifier: Programming Language :: Python :: 3 :: Only
Classifier: Operating System :: OS Independent
Requires-Python: >=3.8
License-File: LICENSE
Requires-Dist: pyvalem>=2.5.10
Requires-Dist: requests>=2.27.1
Requires-Dist: numpy>=1.23.1
Requires-Dist: matplotlib>=3.5.2
Requires-Dist: pyqn>=1.3.1
Provides-Extra: dev
Requires-Dist: black; extra == "dev"
Requires-Dist: pytest-cov; extra == "dev"
Requires-Dist: tox; extra == "dev"
Requires-Dist: ipython; extra == "dev"
Requires-Dist: jupyter; extra == "dev"
Dynamic: author
Dynamic: author-email
Dynamic: classifier
Dynamic: description
Dynamic: description-content-type
Dynamic: home-page
Dynamic: keywords
Dynamic: project-url
Dynamic: provides-extra
Dynamic: requires-dist
Dynamic: requires-python
Dynamic: summary
